solvis_tools-0.1.5.dist-info/METADATA
solvis_tools-0.1.5.dist-info/WHEEL
solvis/__init__.py
solvis/atom_tag_manager.py
solvis/bond_helper.py
solvis/geometric_utils.py
solvis/render_helper.py
solvis/solvation_shell.py
solvis/system.py
solvis/util.py
solvis/vis_initializers.py
solvis/visualization.py
solvis_tools-0.1.5.dist-info/RECORD
