Metadata-Version: 2.1
Name: solvis-tools
Version: 0.1.5
Summary: A module for analyzing and visualizing solvation shells in LAMMPS output files, but would work with most files that can be handled by ASE.
Author-Email: Amrita Goswami <amrita@hi.is>
License: MIT
Classifier: Programming Language :: Python :: 3.10
Requires-Python: >=3.10
Requires-Dist: ase>=3.22.1
Requires-Dist: numpy
Requires-Dist: scipy>=1.7.3
Requires-Dist: pyvista>=0.43.0
Requires-Dist: pillow>=10.0.1
Requires-Dist: imageio>=2.31.5
Requires-Dist: pooch>=1.8.0
Requires-Dist: scooby>=0.9.2
Provides-Extra: test
Requires-Dist: pytest>=6.2.5; extra == "test"
Requires-Dist: coverage>=6.1.1; extra == "test"
Requires-Dist: pytest-cov>=3.0.0; extra == "test"
Provides-Extra: dev
Requires-Dist: flake8>=3.9.2; extra == "dev"
Requires-Dist: mypy>=0.910; extra == "dev"
Requires-Dist: black>=22.3.0; extra == "dev"
Requires-Dist: isort>=5.9.3; extra == "dev"
Requires-Dist: autoflake>=1.4; extra == "dev"
Requires-Dist: flake8-docstrings>=1.6.0; extra == "dev"
Provides-Extra: examples
Requires-Dist: pandas; extra == "examples"
